README.md
setup.py
rxndb_utils/__init__.py
rxndb_utils/db_base.py
rxndb_utils/db_init.py
rxndb_utils/sql_utils.py
rxndb_utils/table_mol.py
rxndb_utils/table_origin_rxn_patent.py
rxndb_utils/table_rxn.py
rxndb_utils.egg-info/PKG-INFO
rxndb_utils.egg-info/SOURCES.txt
rxndb_utils.egg-info/dependency_links.txt
rxndb_utils.egg-info/requires.txt
rxndb_utils.egg-info/top_level.txt